Workbook

Sheet Instructions
A1: PETROL PUMP SOFTWARE - EXCEL VERSION
A3: Welcome!
A5: This workbook is a complete offline management system for your petrol pump with:
A6: • 1 Pump • 2 Tanks (Petrol + Diesel) • English language
A8: SHEETS OVERVIEW
A10: Instructions | B10: This page – start here
A11: Dashboard | B11: Live summary of sales, stock, cash, credit, profit
A12: Settings | B12: Pump details, fuel prices, tank capacity & current stock
A13: Meter Readings | B13: Daily opening & closing meter readings → auto litres sold
A14: Sales | B14: Every sale transaction with payment mode
A15: Fuel Receipts | B15: Tanker deliveries that fill the tanks
A16: Tank Stock | B16: Daily stock movement + variance vs actual dip
A17: Expenses | B17: Salaries, generator, maintenance, other costs
A18: Credit Customers | B18: List of credit customers + outstanding
A19: Credit Transactions | B19: Credit sales and payment collections
A20: Reports | B20: Quick totals and profit snapshot
A23: DAILY ROUTINE (Recommended)
A24: 1. Morning: Enter Opening Meter readings
A25: 2. During day: Enter every Sale in Sales sheet
A26: 3. When tanker arrives: Enter in Fuel Receipts
A27: 4. Evening: Enter Closing Meter readings
A28: 5. Enter expenses of the day
A29: 6. Update Actual Dip in Tank Stock (if you take physical measurement)
A30: 7. Update Current Stock in Settings sheet
A31: 8. Check Dashboard
A33: COLOUR GUIDE
A34: Yellow cells | B34: You can type / edit these (inputs)
A35: Green cells | B35: Calculated automatically – do not overwrite
A36: Blue text | B36: Input values
A38: BACKUP
A39: Copy this entire file to a USB drive or Google Drive / OneDrive every day or every few days.
A40: This is your database backup.
A42: NEXT STEP – FULL SOFTWARE
A43: When you are ready for a proper multi-user offline desktop or web software
A44: (with real login, automatic backup, printer support, better reports),
A45: come back and we will build it on top of this same structure.
A47: Your setup: 1 Pump + 2 Tanks | Offline | English

Sheet Dashboard
A1: PETROL PUMP MANAGEMENT SYSTEM - DASHBOARD
A2: Generated: 09-Aug-2026 04:27 | Offline Excel Version | 1 Pump · 2 Tanks
A4: Select Date | B4: 46243 | C4: ← Change this date to view different day summaries (formulas use TODAY by default)
A6: TODAY'S KEY METRICS
A7: Today's Total Sales (₹) | B7: =SUMIF(Sales!A:A,TEXT(TODAY(),"YYYY-MM-DD"),Sales!G:G) -> 0
A8: Cash Collected Today (₹) | B8: =SUMIFS(Sales!G:G,Sales!A:A,TEXT(TODAY(),"YYYY-MM-DD"),Sales!F:F,"Cash") -> 0
A9: UPI / Card Today (₹) | B9: =SUMIFS(Sales!G:G,Sales!A:A,TEXT(TODAY(),"YYYY-MM-DD"),Sales!F:F,"<>Cash")-SUMIFS(Sales!G:G,Sales!A:A,TEXT(TODAY(),"YYYY-MM-DD"),Sales!F:F,"Credit") -> 0
A10: Credit Sales Today (₹) | B10: =SUMIFS(Sales!G:G,Sales!A:A,TEXT(TODAY(),"YYYY-MM-DD"),Sales!F:F,"Credit") -> 0
A11: Total Expenses Today (₹) | B11: =SUMIF(Expenses!A:A,TEXT(TODAY(),"YYYY-MM-DD"),Expenses!D:D) -> 0
A12: Estimated Daily Profit (₹) | B12: =B7-B11 -> 0
A14: CURRENT FUEL STOCK
A15: Tank | B15: Fuel Type | C15: Current Stock (L) | D15: Capacity (L) | E15: % Full | F15: Status
A16: Tank 1 | B16: Petrol | C16: =Settings!D17 -> 12500 | D16: =Settings!C17 -> 20000 | E16: =IF(D16=0,0,C16/D16) -> 0.625 | F16: =IF(E16<0.2,"LOW STOCK",IF(E16<0.4,"Reorder Soon","OK")) -> OK
A17: Tank 2 | B17: Diesel | C17: =Settings!D18 -> 9800 | D17: =Settings!C18 -> 15000 | E17: =IF(D17=0,0,C17/D17) -> 0.65333333 | F17: =IF(E17<0.2,"LOW STOCK",IF(E17<0.4,"Reorder Soon","OK")) -> OK
A19: CREDIT OUTSTANDING
A20: Total Outstanding Credit (₹) | B20: =SUMIF('Credit Customers'!E:E,">0",'Credit Customers'!E:E) -> 24150
A22: HOW TO USE THIS WORKBOOK
A23: 1. Go to SETTINGS sheet first → Enter your pump name, fuel prices, tank capacities and current stock.
A24: 2. Every day: Enter Opening & Closing Meter Readings in METER READINGS sheet.
A25: 3. Record every sale in SALES sheet (Date, Pump, Liters, Payment mode).
A26: 4. When tanker comes: Enter receipt in FUEL RECEIPTS sheet.
A27: 5. Record expenses in EXPENSES sheet.
A28: 6. Manage credit customers in CREDIT CUSTOMERS and CREDIT TRANSACTIONS sheets.
A29: 7. Dashboard and REPORTS update automatically using formulas.
A30: 8. Yellow cells = your inputs (type in them). Green cells = calculated (do not edit).
A31: 9. This file works 100% offline. Take daily backup by copying the file to USB/Drive.

Sheet Settings
A1: SETTINGS & MASTER DATA
A3: PETROL PUMP INFORMATION
A4: Pump Name | B4: My Petrol Pump
A5: Address | B5: Your Address Here
A6: Owner / Manager Name | B6: Owner Name
A7: Contact Number | B7: 9876543210
A8: GSTIN (if any)
A10: FUEL PRICES (₹ per Litre) - Update when price changes
A11: Fuel | B11: Current Price (₹/L) | C11: Last Updated
A12: Petrol | B12: 102.5 | C12: 46243
A13: Diesel | B13: 90.75 | C13: 46243
A15: TANK CAPACITY & CURRENT STOCK
A16: Tank | B16: Fuel Type | C16: Capacity (Litres) | D16: Current Stock (L) ← Update after every dip / day
A17: Tank 1 | B17: Petrol | C17: 20000 | D17: 12500
A18: Tank 2 | B18: Diesel | C18: 15000 | D18: 9800
A20: Note: After physical dip or end of day, update Current Stock (column D) above.
A22: PUMP / NOZZLE CONFIGURATION (1 Pump with 2 Nozzles)
A23: Pump No. | B23: Connected Tank / Fuel | C23: Notes
A24: Pump 1 - Nozzle 1 | B24: Petrol (Tank 1) | C24: Main road side
A25: Pump 1 - Nozzle 2 | B25: Diesel (Tank 2) | C25: Highway side
A27: USER ROLES (Manual for Excel)
A28: Admin: Full access (you)
A29: Manager: Can edit sales, stock, expenses, credit
A30: Operator: Can only enter meter readings & sales
A31: Tip: Protect sheets with password (Review → Protect Sheet) for real control.

Sheet Meter Readings
A1: METER READINGS (Daily)
A2: Enter Opening reading at start of day / shift. Enter Closing at end. Total Sold is auto-calculated.
A4: Date | B4: Pump | C4: Fuel | D4: Opening Meter | E4: Closing Meter | F4: Total Litres Sold | G4: Shift / Notes | H4: Entered By
A5: 46238 | B5: Pump 1 | C5: Petrol | D5: 125176 | E5: 126018.18 | F5: =E5-D5 -> 842.18 | G5: Day | H5: Operator
A6: 46238 | B6: Pump 1 | C6: Diesel | D6: 89083 | E6: 89720.51 | F6: =E6-D6 -> 637.51 | G6: Day | H6: Operator
A7: 46239 | B7: Pump 1 | C7: Petrol | D7: 125294 | E7: 126728.96 | F7: =E7-D7 -> 1434.96 | G7: Day | H7: Operator
A8: 46239 | B8: Pump 1 | C8: Diesel | D8: 89166 | E8: 90186.19 | F8: =E8-D8 -> 1020.19 | G8: Day | H8: Operator
A9: 46240 | B9: Pump 1 | C9: Petrol | D9: 125105 | E9: 126506.54 | F9: =E9-D9 -> 1401.54 | G9: Day | H9: Operator
A10: 46240 | B10: Pump 1 | C10: Diesel | D10: 89170 | E10: 90093.27 | F10: =E10-D10 -> 923.27 | G10: Day | H10: Operator
A11: 46241 | B11: Pump 1 | C11: Petrol | D11: 125302 | E11: 126490.05 | F11: =E11-D11 -> 1188.05 | G11: Day | H11: Operator
A12: 46241 | B12: Pump 1 | C12: Diesel | D12: 89110 | E12: 90090.32 | F12: =E12-D12 -> 980.32 | G12: Day | H12: Operator
A13: 46242 | B13: Pump 1 | C13: Petrol | D13: 125002 | E13: 126536.96 | F13: =E13-D13 -> 1534.96 | G13: Day | H13: Operator
A14: 46242 | B14: Pump 1 | C14: Diesel | D14: 89295 | E14: 90646.03 | F14: =E14-D14 -> 1351.03 | G14: Day | H14: Operator
F15: =IF(OR(D15="",E15=""),"",E15-D15)
F16: =IF(OR(D16="",E16=""),"",E16-D16)
F17: =IF(OR(D17="",E17=""),"",E17-D17)
F18: =IF(OR(D18="",E18=""),"",E18-D18)
F19: =IF(OR(D19="",E19=""),"",E19-D19)
F20: =IF(OR(D20="",E20=""),"",E20-D20)
F21: =IF(OR(D21="",E21=""),"",E21-D21)
F22: =IF(OR(D22="",E22=""),"",E22-D22)
F23: =IF(OR(D23="",E23=""),"",E23-D23)
F24: =IF(OR(D24="",E24=""),"",E24-D24)

Sheet Sales

Sheet Fuel Receipts
A1: FUEL RECEIPTS (Tanker Deliveries)
A2: Enter every tanker delivery. This increases tank stock.
A4: Date | B4: Invoice / Challan No. | C4: Supplier | D4: Fuel | E4: Quantity Received (L) | H4: Notes
A5: 46240 | B5: INV-78451 | C5: IOCL Depot | D5: Petrol | E5: 8000 | H5: Morning delivery
A6: 46241 | B6: INV-78489 | C6: HPCL | D6: Diesel | E6: 6000
E7: 5000

Sheet Tank Stock
A1: TANK STOCK & VARIANCE
A2: Daily stock movement. Closing Stock = Opening + Received - Sold. Variance = Book Closing - Actual Dip.
A4: Date | B4: Tank | C4: Fuel | D4: Opening Stock (L) | E4: Received (L) | F4: Sold (L) | G4: Book Closing (L) | H4: Actual Dip (L) | I4: Variance (L) | J4: Notes
A5: 46238 | B5: Tank 1 | C5: Petrol | D5: 12000 | E5: 8000 | F5: 1355.12 | G5: =D5+E5-F5 -> 18644.88 | I5: =IF(H5="", "", G5-H5)
A6: 46238 | B6: Tank 2 | C6: Diesel | D6: 9500 | E6: 0 | F6: 746.27 | G6: =D6+E6-F6 -> 8753.73 | I6: =IF(H6="", "", G6-H6)
A7: 46239 | B7: Tank 1 | C7: Petrol | D7: 12100 | E7: 0 | F7: 1205.49 | G7: =D7+E7-F7 -> 10894.51 | I7: =IF(H7="", "", G7-H7)
A8: 46239 | B8: Tank 2 | C8: Diesel | D8: 9580 | E8: 6000 | F8: 777.19 | G8: =D8+E8-F8 -> 14802.81 | I8: =IF(H8="", "", G8-H8)
A9: 46240 | B9: Tank 1 | C9: Petrol | D9: 12200 | E9: 0 | F9: 1424.27 | G9: =D9+E9-F9 -> 10775.73 | I9: =IF(H9="", "", G9-H9)
A10: 46240 | B10: Tank 2 | C10: Diesel | D10: 9660 | E10: 0 | F10: 799.76 | G10: =D10+E10-F10 -> 8860.24 | I10: =IF(H10="", "", G10-H10)
A11: 46241 | B11: Tank 1 | C11: Petrol | D11: 12300 | E11: 0 | F11: 973.83 | G11: =D11+E11-F11 -> 11326.17 | I11: =IF(H11="", "", G11-H11)
A12: 46241 | B12: Tank 2 | C12: Diesel | D12: 9740 | E12: 0 | F12: 739.13 | G12: =D12+E12-F12 -> 9000.87 | I12: =IF(H12="", "", G12-H12)
A13: 46242 | B13: Tank 1 | C13: Petrol | D13: 12400 | E13: 0 | F13: 1568.78 | G13: =D13+E13-F13 -> 10831.22 | I13: =IF(H13="", "", G13-H13)
A14: 46242 | B14: Tank 2 | C14: Diesel | D14: 9820 | E14: 0 | F14: 800.03 | G14: =D14+E14-F14 -> 9019.97 | I14: =IF(H14="", "", G14-H14)
G15: =IF(D15="","",D15+E15-F15) | I15: =IF(OR(H15="",G15=""),"",G15-H15)
G16: =IF(D16="","",D16+E16-F16) | I16: =IF(OR(H16="",G16=""),"",G16-H16)
G17: =IF(D17="","",D17+E17-F17) | I17: =IF(OR(H17="",G17=""),"",G17-H17)
G18: =IF(D18="","",D18+E18-F18) | I18: =IF(OR(H18="",G18=""),"",G18-H18)
G19: =IF(D19="","",D19+E19-F19) | I19: =IF(OR(H19="",G19=""),"",G19-H19)
G20: =IF(D20="","",D20+E20-F20) | I20: =IF(OR(H20="",G20=""),"",G20-H20)
G21: =IF(D21="","",D21+E21-F21) | I21: =IF(OR(H21="",G21=""),"",G21-H21)
G22: =IF(D22="","",D22+E22-F22) | I22: =IF(OR(H22="",G22=""),"",G22-H22)
G23: =IF(D23="","",D23+E23-F23) | I23: =IF(OR(H23="",G23=""),"",G23-H23)
G24: =IF(D24="","",D24+E24-F24) | I24: =IF(OR(H24="",G24=""),"",G24-H24)

Sheet Expenses
A1: EXPENSE MANAGEMENT
A4: Date | B4: Category | C4: Description | D4: Amount (₹) | E4: Paid By | F4: Notes
A5: 46242 | B5: Salary | C5: Staff salary - Week | D5: 8500 | E5: Cash
A6: 46241 | B6: Generator Fuel | C6: Diesel for generator | D6: 1200 | E6: Cash
A7: 46240 | B7: Maintenance | C7: Nozzle repair | D7: 750 | E7: UPI | F7: Pump 1
A8: 46239 | B8: Other | C8: Tea & misc | D8: 200 | E8: Cash

Sheet Credit Customers
A1: CREDIT CUSTOMERS MASTER
A4: Customer ID | B4: Customer Name | C4: Phone | D4: Vehicle / Firm | E4: Outstanding (₹) | F4: Credit Limit (₹)
A5: C001 | B5: Sharma Transport | C5: 9876501234 | D5: MH12AB1234 | E5: 12500 | F5: 50000
A6: C002 | B6: Patil Brothers | C6: 9822012345 | D6: MH14CD5678 | E6: 8200 | F6: 30000
A7: C003 | B7: Local Taxi Stand | C7: 9765432109 | D7: Multiple | E7: 3450 | F7: 15000
A8: C004 | B8: Mr. Deshmukh | C8: 9881234567 | D8: MH12EF9012 | E8: 0 | F8: 10000
A25: Note: Outstanding is updated manually or from Credit Transactions sheet. Keep this list updated.

Sheet Credit Transactions
A1: CREDIT SALES & COLLECTIONS
A4: Date | B4: Customer ID | C4: Customer Name | D4: Type | E4: Amount (₹) | F4: Reference / Bill | G4: Notes
A5: 46242 | B5: C001 | C5: Sharma Transport | D5: Credit Sale | E5: 4500 | F5: Sale #1023
A6: 46241 | B6: C002 | C6: Patil Brothers | D6: Credit Sale | E6: 3200 | F6: Sale #1018
A7: 46240 | B7: C001 | C7: Sharma Transport | D7: Payment Received | E7: -5000 | F7: Cash | G7: Partial payment
A8: 46239 | B8: C003 | C8: Local Taxi Stand | D8: Credit Sale | E8: 1800 | F8: Sale #1009

Sheet Reports
A1: REPORTS & SUMMARIES
A3: DAILY SALES SUMMARY (Auto from Sales sheet)
A4: Metric | B4: Value
A5: Total Sales Amount (All time sample) | B5: =SUM(Sales!G:G) -> 0
A6: Total Petrol Litres Sold | B6: =SUMIF(Sales!D:D,"Petrol",Sales!E:E) -> 0
A7: Total Diesel Litres Sold | B7: =SUMIF(Sales!D:D,"Diesel",Sales!E:E) -> 0
A8: Cash Sales Total | B8: =SUMIF(Sales!F:F,"Cash",Sales!G:G) -> 0
A9: Credit Sales Total | B9: =SUMIF(Sales!F:F,"Credit",Sales!G:G) -> 0
A11: EXPENSE TOTAL
A12: All Expenses (sample period) | B12: =SUM(Expenses!D:D) -> 10650
A14: PROFIT SNAPSHOT (Approximate)
A15: Sales - Expenses | B15: =B5-B12 -> -10650
A17: STOCK VARIANCE (from Tank Stock sheet)
A18: Note: Review Tank Stock sheet regularly. Positive variance = book higher than actual (possible loss/theft/evaporation).
A20: HOW TO GET MORE REPORTS
A21: • Filter any sheet by Date column (Data → Filter)
A22: • Use Pivot Tables for monthly summaries (Insert → PivotTable)
A23: • Copy Dashboard or this sheet values for daily printout
A24: • For full software later: we can add automatic PDF daily reports, WhatsApp alerts, multi-user login etc.
